lab_2/controller.v
`timescale 1ns/1ps

module controller(
    input  wire clk,
    input  wire rst,
    input  wire go,
    input  wire count_ge_n,
    output reg  load,
    output reg  step,
    output reg  done
);

    localparam IDLE = 2'b00,
               INIT = 2'b01,
               CALC = 2'b10,
               DONE = 2'b11;

    reg [1:0] state, next;

    always @(posedge clk or posedge rst) begin
        if (rst)
            state <= IDLE;
        else
            state <= next;
    end

    always @(*) begin
        load = 0;
        step = 0;
        done = 0;
        next = state;

        case (state)
            IDLE: if (go) next = INIT;

            INIT: begin
                load = 1;
                next = CALC;
            end

            CALC: begin
                if (count_ge_n)
                    next = DONE;
                else
                    step = 1;
            end

            DONE: begin
                done = 1;
                if (!go) next = IDLE;
            end
        endcase
    end

endmodule

lab_2/datapath.v
`timescale 1ns/1ps

module datapath #(parameter WIDTH=8)(
    input  wire             clk,
    input  wire             rst,
    input  wire             load,
    input  wire             step,
    input  wire [WIDTH-1:0] n,
    output wire             count_ge_n,
    output reg  [WIDTH-1:0] result
);

    reg [WIDTH-1:0] a, b, count;

    assign count_ge_n = (count >= n);

    always @(posedge clk or posedge rst) begin
        if (rst) begin
            a      <= 0;
            b      <= 1;
            count  <= 0;
            result <= 0;
        end else if (load) begin
            a      <= 0;
            b      <= 1;
            count  <= 0;
            result <= 0;
        end else if (step) begin
            result <= a;   // capture current Fibonacci number
            a      <= b;
            b      <= a + b;
            count  <= count + 1;
        end
    end

endmodule

lab_2/fib_tb.v
`timescale 1ns/1ps

module fib_tb;

    parameter WIDTH = 8;

    // Testbench signals
    reg clk;
    reg rst;
    reg go;
    reg [WIDTH-1:0] n;

    wire load;
    wire step;
    wire done;
    wire count_ge_n;
    wire [WIDTH-1:0] result;

    // Instantiate datapath
    datapath #(WIDTH) dp (
        .clk(clk),
        .rst(rst),
        .load(load),
        .step(step),
        .n(n),
        .count_ge_n(count_ge_n),
        .result(result)
    );

    // Instantiate controller
    controller ctrl (
        .clk(clk),
        .rst(rst),
        .go(go),
        .count_ge_n(count_ge_n),
        .load(load),
        .step(step),
        .done(done)
    );

    // Clock generation
    always #5 clk = ~clk;

    // VCD dump
    initial begin
        $dumpfile("fib_tb.vcd");
        $dumpvars(0, fib_tb);
    end

    // Test procedure
    initial begin
        clk = 0;
        rst = 1;
        go = 0;
        n = 0;

        #10 rst = 0;

        // Fibonacci(5)
        n = 5; go = 1; #10 go = 0;
        wait(done);
        $display("Fibonacci(5) = %0d", result);

        #20;
        n = 7; go = 1; #10 go = 0;
        wait(done);
        $display("Fibonacci(7) = %0d", result);

        #20;
        n = 10; go = 1; #10 go = 0;
        wait(done);
        $display("Fibonacci(10) = %0d", result);

        $finish;
    end

endmodule

lab_2/fib_tb.vcd
$date
	Mon Feb  2 21:55:15 2026
$end

$version
	Synopsys VCS version V-2023.12-SP2-1_Full64
$end

$timescale
	1ps
$end

$comment Csum: 1 637595ffcad48446 $end


$scope module fib_tb $end
$var reg 1 ! clk $end
$var reg 1 " rst $end
$var reg 1 # go $end
$var reg 8 $ n [7:0] $end
$var wire 1 % load $end
$var wire 1 & step $end
$var wire 1 ' done $end
$var wire 1 ( count_ge_n $end
$var wire 8 ) result [7:0] $end

$scope module dp $end
$var wire 1 ! clk $end
$var wire 1 " rst $end
$var wire 1 % load $end
$var wire 1 & step $end
$var wire 8 $ n [7:0] $end
$var wire 1 ( count_ge_n $end
$var reg 8 ) result [7:0] $end
$var reg 8 * a [7:0] $end
$var reg 8 + b [7:0] $end
$var reg 8 , count [7:0] $end
$upscope $end


$scope module ctrl $end
$var wire 1 ! clk $end
$var wire 1 " rst $end
$var wire 1 # go $end
$var wire 1 ( count_ge_n $end
$var reg 1 % load $end
$var reg 1 & step $end
$var reg 1 ' done $end
$var reg 2 - state [1:0] $end
$var reg 2 . next [1:0] $end
$upscope $end

$upscope $end

$enddefinitions $end

#0
$dumpvars
0!
1(
0'
0%
0&
0#
1"
b00000000 *
b00000001 +
b00000000 ,
b00000000 )
b00000000 $
b00 .
b00 -
$end
#5000
1!
#10000
0"
b00000101 $
0(
1#
0!
b01 .
#15000
1!
b01 -
1%
b10 .
#20000
0#
0!
#25000
1!
b10 -
0%
1&
#30000
0!
#35000
1!
b00000001 *
b00000001 ,
#40000
0!
#45000
1!
b00000001 )
b00000010 +
b00000010 ,
#50000
0!
#55000
1!
b00000010 *
b00000011 +
b00000011 ,
#60000
0!
#65000
1!
b00000010 )
b00000011 *
b00000101 +
b00000100 ,
#70000
0!
#75000
1!
b00000011 )
b00000101 *
b00001000 +
b00000101 ,
1(
0&
b11 .
#80000
0!
#85000
1!
b11 -
1'
b00 .
#90000
0!
#95000
1!
b00 -
0'
#100000
0!
#105000
b00000111 $
0(
1#
1!
b01 .
b01 -
1%
b10 .
#110000
0!
#115000
0#
1!
b00000000 )
b00000000 *
b00000001 +
b00000000 ,
b10 -
0%
1&
#120000
0!
#125000
1!
b00000001 *
b00000001 ,
#130000
0!
#135000
1!
b00000001 )
b00000010 +
b00000010 ,
#140000
0!
#145000
1!
b00000010 *
b00000011 +
b00000011 ,
#150000
0!
#155000
1!
b00000010 )
b00000011 *
b00000101 +
b00000100 ,
#160000
0!
#165000
1!
b00000011 )
b00000101 *
b00001000 +
b00000101 ,
#170000
0!
#175000
1!
b00000101 )
b00001000 *
b00001101 +
b00000110 ,
#180000
0!
#185000
1!
b00001000 )
b00001101 *
b00010101 +
b00000111 ,
1(
0&
b11 .
#190000
0!
#195000
1!
b11 -
1'
b00 .
#200000
0!
#205000
1!
b00 -
0'
#210000
0!
#215000
b00001010 $
0(
1#
1!
b01 .
b01 -
1%
b10 .
#220000
0!
#225000
0#
1!
b00000000 )
b00000000 *
b00000001 +
b00000000 ,
b10 -
0%
1&
#230000
0!
#235000
1!
b00000001 *
b00000001 ,
#240000
0!
#245000
1!
b00000001 )
b00000010 +
b00000010 ,
#250000
0!
#255000
1!
b00000010 *
b00000011 +
b00000011 ,
#260000
0!
#265000
1!
b00000010 )
b00000011 *
b00000101 +
b00000100 ,
#270000
0!
#275000
1!
b00000011 )
b00000101 *
b00001000 +
b00000101 ,
#280000
0!
#285000
1!
b00000101 )
b00001000 *
b00001101 +
b00000110 ,
#290000
0!
#295000
1!
b00001000 )
b00001101 *
b00010101 +
b00000111 ,
#300000
0!
#305000
1!
b00001101 )
b00010101 *
b00100010 +
b00001000 ,
#310000
0!
#315000
1!
b00010101 )
b00100010 *
b00110111 +
b00001001 ,
#320000
0!
#325000
1!
b00100010 )
b00110111 *
b01011001 +
b00001010 ,
1(
0&
b11 .
#330000
0!
#335000
1!
b11 -
1'
b00 .
